INSTALL.rst
MANIFEST.in
MIGRATION.rst
Makefile
NEWS.rst
README.rst
setup.py
src/ll/__init__.py
src/ll/nightshade.py
src/ll_nightshade.egg-info/PKG-INFO
src/ll_nightshade.egg-info/SOURCES.txt
src/ll_nightshade.egg-info/dependency_links.txt
src/ll_nightshade.egg-info/namespace_packages.txt
src/ll_nightshade.egg-info/not-zip-safe
src/ll_nightshade.egg-info/requires.txt
src/ll_nightshade.egg-info/top_level.txt